Metadata-Version: 2.1
Name: natalie
Version: 2.9
Summary: an automation software made for my friend natalie
Author: jack
Author-email: kinginjack@gmail.com
License: GPL-3.0
Platform: UNKNOWN
Requires-Python: >=3.8
